hatch_build_freeze/__init__.py
hatch_build_freeze/hooks.py
hatch_build_freeze/logger.py
hatch_build_freeze/plugin.py
hatch_build_freeze-1.1.0.dist-info/METADATA
hatch_build_freeze-1.1.0.dist-info/WHEEL
hatch_build_freeze-1.1.0.dist-info/entry_points.txt
hatch_build_freeze-1.1.0.dist-info/licenses/LICENSE
hatch_build_freeze-1.1.0.dist-info/RECORD
