Metadata-Version: 2.4
Name: hatch-build-freeze
Version: 1.1.0
Summary: Hatch Dependency Freezing Plugin: Enhancing Build Consistency
Author-email: "minds.ai, Inc." <contact@minds.ai>
License-Expression: Apache-2.0
License-File: LICENSE
Classifier: Development Status :: 5 - Production/Stable
Classifier: Framework :: Hatch
Classifier: Programming Language :: Python
Classifier: Programming Language :: Python :: 3.10
Classifier: Programming Language :: Python :: 3.11
Classifier: Programming Language :: Python :: 3.12
Classifier: Topic :: Software Development :: Build Tools
Classifier: Typing :: Typed
Requires-Python: >=3.10
Requires-Dist: hatchling>=1.6.0
Requires-Dist: tomlkit>=0.13.0
